vintasend_jinja/__init__.py
vintasend_jinja/py.typed
vintasend_jinja/services/__init__.py
vintasend_jinja/services/notification_template_renderers/__init__.py
vintasend_jinja/services/notification_template_renderers/jinja_templated_email_renderer.py
vintasend_jinja/services/tests/__init__.py
vintasend_jinja/services/tests/test_template_renderers.py
vintasend_jinja/templates/vintasend_jinja/emails/base_notification.html
vintasend_jinja/templates/vintasend_jinja/emails/test/test_templated_email_body.html
vintasend_jinja/templates/vintasend_jinja/emails/test/test_templated_email_preheader.html
vintasend_jinja/templates/vintasend_jinja/emails/test/test_templated_email_subject.txt
vintasend_jinja-0.1.4.dist-info/LICENSE.txt
vintasend_jinja-0.1.4.dist-info/METADATA
vintasend_jinja-0.1.4.dist-info/WHEEL
vintasend_jinja-0.1.4.dist-info/RECORD
